etw/__init__.py
etw/etw.py
etw/version.py
etw-0.0.0.dist-info/LICENSE
etw-0.0.0.dist-info/METADATA
etw-0.0.0.dist-info/WHEEL
etw-0.0.0.dist-info/top_level.txt
etw-0.0.0.dist-info/RECORD
