Metadata-Version: 2.1
Name: etw
Version: 0.0.0
Summary: Edge Time Warp
Home-page: https://github.com/Equinor/etw
Author: Equinor
Author-email: jegm@equinor.com
License: GNU Lesser General Public License v3
Project-URL: Documentation, https://etw.readthedocs.io/
Project-URL: Issue Tracker, https://github.com/Equinor/etw/issues
Platform: any
